numeroPrimo/__init__.py
numeroPrimo/primo.py
numeroPrimo/test.py
verificanumeroprimo-1.0.0.dist-info/METADATA
verificanumeroprimo-1.0.0.dist-info/WHEEL
verificanumeroprimo-1.0.0.dist-info/top_level.txt
verificanumeroprimo-1.0.0.dist-info/RECORD
