Metadata-Version: 2.1
Name: verificanumeroprimo
Version: 1.0.0
Summary: Pacote para verificar se um numero eh primo
Home-page: UNKNOWN
Author: Luiz Claudio
Author-email: luiz.holanda@visionaespacial.com.br
License: UNKNOWN
Platform: UNKNOWN
